<!--
Disabled by https-everywhere-checker because:
Fetch error: http://intevation.de/ => https://intevation.de/: (28, 'Connection timed out after 10000 milliseconds')
Fetch error: http://ftp.intevation.de/ => https://ftp.intevation.de/: (28, 'Connection timed out after 10000 milliseconds')
Fetch error: http://ssl.intevation.de/ => https://ssl.intevation.de/: (28, 'Connection timed out after 10001 milliseconds')
Fetch error: http://www.intevation.de/ => https://www.intevation.de/: (28, 'Connection timed out after 10000 milliseconds')
Fetch error: http://intevation.net/ => https://intevation.de/: (28, 'Connection timed out after 10001 milliseconds')
Fetch error: http://ftp.intevation.net/ => https://ftp.intevation.de/: (28, 'Connection timed out after 10000 milliseconds')
Fetch error: http://ssl.intevation.net/ => https://ssl.intevation.de/: (28, 'Connection timed out after 10000 milliseconds')
Fetch error: http://www.intevation.net/ => https://www.intevation.de/: (28, 'Connection timed out after 10000 milliseconds')
Fetch error: http://intevation.org/ => https://intevation.de/: (28, 'Connection timed out after 10001 milliseconds')
Fetch error: http://ftp.intevation.org/ => https://ftp.intevation.de/: (28, 'Connection timed out after 10000 milliseconds')
Fetch error: http://ssl.intevation.org/ => https://ssl.intevation.de/: (28, 'Connection timed out after 10000 milliseconds')
Fetch error: http://www.intevation.org/ => https://www.intevation.de/: (28, 'Connection timed out after 10001 milliseconds')
-->
<ruleset name="Intevation GmbH (partial)" default_off='failed ruleset test'>
	<target host="intevation.de" />
	<target host="ftp.intevation.de" />
	<target host="ssl.intevation.de" />
	<target host="www.intevation.de" />
	<target host="intevation.net" />
	<target host="ftp.intevation.net" />
	<target host="ssl.intevation.net" />
	<target host="www.intevation.net" />
	<target host="intevation.org" />
	<target host="ftp.intevation.org" />
	<target host="ssl.intevation.org" />
	<target host="www.intevation.org" />

	<securecookie host="^(?:ssl|www)\.intevation\.de$"
			name=".+" />

	<rule from="^http://((ftp|ssl|www)\.)?intevation\.(de|net|org)/"
		to="https://$1intevation.de/" />
</ruleset>
